trustchain/__init__.py
trustchain/cli.py
trustchain/integrations/__init__.py
trustchain/integrations/django.py
trustchain/integrations/fastapi.py
trustchain/integrations/flask.py
trustchain/integrations/langchain.py
trustchain/integrations/mcp.py
trustchain/ui/__init__.py
trustchain/ui/explorer.py
trustchain/utils/__init__.py
trustchain/utils/exceptions.py
trustchain/v2/__init__.py
trustchain/v2/config.py
trustchain/v2/core.py
trustchain/v2/events.py
trustchain/v2/graph.py
trustchain/v2/logging.py
trustchain/v2/merkle.py
trustchain/v2/metrics.py
trustchain/v2/nonce_storage.py
trustchain/v2/policy.py
trustchain/v2/policy_hooks.py
trustchain/v2/reasoning.py
trustchain/v2/schemas.py
trustchain/v2/server.py
trustchain/v2/session.py
trustchain/v2/signer.py
trustchain/v2/storage.py
trustchain/v2/tenants.py
trustchain/v2/tsa.py
trustchain/v2/verifier.py
trustchain-2.3.0.dist-info/licenses/LICENSE
trustchain-2.3.0.dist-info/licenses/NOTICE.md
trustchain-2.3.0.dist-info/METADATA
trustchain-2.3.0.dist-info/WHEEL
trustchain-2.3.0.dist-info/entry_points.txt
trustchain-2.3.0.dist-info/top_level.txt
trustchain-2.3.0.dist-info/RECORD
