Metadata-Version: 2.4
Name: trustchain
Version: 2.3.0
Summary: Cryptographically signed AI tool responses for preventing hallucinations
Author-email: Ed Cherednik <edcherednik@gmail.com>
License: MIT
Project-URL: Homepage, https://github.com/petro1eum/trust_chain
Project-URL: Documentation, https://trustchain.readthedocs.io/
Project-URL: Repository, https://github.com/petro1eum/trust_chain.git
Project-URL: Bug Tracker, https://github.com/petro1eum/trust_chain/issues
Keywords: ai,security,cryptography,signatures,blockchain,trust
Classifier: Development Status :: 4 - Beta
Classifier: Intended Audience :: Developers
Classifier: Topic :: Security :: Cryptography
Classifier: Topic :: Scientific/Engineering :: Artificial Intelligence
Classifier: License :: OSI Approved :: MIT License
Classifier: Programming Language :: Python :: 3
Classifier: Programming Language :: Python :: 3.10
Classifier: Programming Language :: Python :: 3.11
Classifier: Programming Language :: Python :: 3.12
Classifier: Programming Language :: Python :: 3.13
Requires-Python: >=3.10
License-File: LICENSE
License-File: NOTICE.md
Requires-Dist: PyNaCl>=1.5.0
Requires-Dist: cryptography>=41.0.0
Requires-Dist: pydantic>=2.0.0
Requires-Dist: msgpack>=1.0.0
Requires-Dist: click>=8.0.0
Requires-Dist: rich>=13.0.0
Requires-Dist: typer>=0.9.0
Requires-Dist: pyyaml>=6.0
Requires-Dist: python-dotenv>=1.0.0
Provides-Extra: fastapi
Requires-Dist: fastapi>=0.104.0; extra == "fastapi"
Requires-Dist: starlette>=0.27.0; extra == "fastapi"
Provides-Extra: flask
Requires-Dist: flask>=2.0.0; extra == "flask"
Provides-Extra: django
Requires-Dist: django>=4.0.0; extra == "django"
Provides-Extra: drf
Requires-Dist: django>=4.0.0; extra == "drf"
Requires-Dist: djangorestframework>=3.14.0; extra == "drf"
Provides-Extra: frameworks
Requires-Dist: fastapi>=0.104.0; extra == "frameworks"
Requires-Dist: starlette>=0.27.0; extra == "frameworks"
Requires-Dist: flask>=2.0.0; extra == "frameworks"
Requires-Dist: django>=4.0.0; extra == "frameworks"
Provides-Extra: kafka
Requires-Dist: kafka-python>=2.0.0; extra == "kafka"
Requires-Dist: aiokafka>=0.10.0; extra == "kafka"
Requires-Dist: confluent-kafka>=2.3.0; extra == "kafka"
Provides-Extra: redis
Requires-Dist: redis>=5.0.0; extra == "redis"
Requires-Dist: aioredis>=2.0.0; extra == "redis"
Provides-Extra: blockchain
Requires-Dist: web3>=6.0.0; extra == "blockchain"
Requires-Dist: ipfshttpclient>=0.8.0; extra == "blockchain"
Provides-Extra: web
Requires-Dist: fastapi>=0.104.0; extra == "web"
Requires-Dist: uvicorn>=0.24.0; extra == "web"
Requires-Dist: pydantic>=2.0.0; extra == "web"
Requires-Dist: websockets>=11.0.0; extra == "web"
Provides-Extra: monitoring
Requires-Dist: prometheus-client>=0.19.0; extra == "monitoring"
Requires-Dist: grafana-api>=1.0.0; extra == "monitoring"
Requires-Dist: fastapi>=0.104.0; extra == "monitoring"
Requires-Dist: uvicorn>=0.24.0; extra == "monitoring"
Provides-Extra: ai
Requires-Dist: langchain>=0.1.0; extra == "ai"
Requires-Dist: langchain-core>=0.1.0; extra == "ai"
Requires-Dist: openai>=1.0.0; extra == "ai"
Requires-Dist: anthropic>=0.8.0; extra == "ai"
Provides-Extra: mcp
Requires-Dist: mcp>=1.0.0; extra == "mcp"
Provides-Extra: integrations
Requires-Dist: langchain-core>=0.1.0; extra == "integrations"
Requires-Dist: mcp>=1.0.0; extra == "integrations"
Provides-Extra: all
Requires-Dist: fastapi>=0.104.0; extra == "all"
Requires-Dist: starlette>=0.27.0; extra == "all"
Requires-Dist: flask>=2.0.0; extra == "all"
Requires-Dist: django>=4.0.0; extra == "all"
Requires-Dist: langchain-core>=0.1.0; extra == "all"
Requires-Dist: mcp>=1.0.0; extra == "all"
Provides-Extra: dev
Requires-Dist: pytest>=7.0.0; extra == "dev"
Requires-Dist: pytest-asyncio>=0.23.0; extra == "dev"
Requires-Dist: pytest-cov>=4.0.0; extra == "dev"
Requires-Dist: black==24.8.0; extra == "dev"
Requires-Dist: isort==5.13.2; extra == "dev"
Requires-Dist: mypy>=1.0.0; extra == "dev"
Requires-Dist: pre-commit>=3.0.0; extra == "dev"
Requires-Dist: coverage>=7.0.0; extra == "dev"
Requires-Dist: ruff>=0.1.0; extra == "dev"
Dynamic: license-file
